streamed_yaml/__init__.py
streamed_yaml/__init__.pyi
streamed_yaml/chunked.py
streamed_yaml/parser.py
streamed_yaml-0.1.3.dist-info/METADATA
streamed_yaml-0.1.3.dist-info/WHEEL
streamed_yaml-0.1.3.dist-info/top_level.txt
streamed_yaml-0.1.3.dist-info/RECORD
