Metadata-Version: 2.1
Name: streamed-yaml
Version: 0.1.3
Summary: Parse streamed (incomplete) single-level YAML
Author-email: Marcel Claramunt <marcel@moveread.com>
Project-URL: repo, https://github.com/marciclabas/streamed-yaml.git
Requires-Python: >=3.10
Requires-Dist: lazy-loader
